ez_prompt/__init__.py
ez_prompt/clean.py
ez_prompt/data.py
ez_prompt/exceptions.py
ez_prompt/models.py
ez_prompt/prompt.py
ez_prompt/warnings.py
ez_prompt-0.1.3.dist-info/LICENSE
ez_prompt-0.1.3.dist-info/METADATA
ez_prompt-0.1.3.dist-info/WHEEL
ez_prompt-0.1.3.dist-info/RECORD
