Metadata-Version: 2.1
Name: ez-prompt
Version: 0.1.3
Summary: An easy-to-use library for creating and seinding prompts to LLMs.
Author: Connor Skelland
Author-email: 34070858+Connor56@users.noreply.github.com
Requires-Python: >=3.11,<4.0
Classifier: Programming Language :: Python :: 3
Classifier: Programming Language :: Python :: 3.11
Classifier: Programming Language :: Python :: 3.12
Requires-Dist: jinja2 (>=3.1.6,<4.0.0)
Requires-Dist: numpy (>=2.2.4,<3.0.0)
Requires-Dist: openai (>=1.72.0,<2.0.0)
Requires-Dist: pandas (>=2.2.3,<3.0.0)
Requires-Dist: platformdirs (>=4.3.7,<5.0.0)
Requires-Dist: pytest (>=8.3.5,<9.0.0)
Requires-Dist: pytest-asyncio (>=0.26.0,<0.27.0)
Requires-Dist: pytest-snapshot (>=0.9.0,<0.10.0)
Requires-Dist: python-dotenv (>=1.1.0,<2.0.0)
Requires-Dist: requests (>=2.32.3,<3.0.0)
Requires-Dist: tiktoken (>=0.9.0,<0.10.0)
